fdplib/__init__.py
fdplib/darab.py
fdplib/errors.py
fdplib/track_classes.py
fdplib/track_tools.py
fdplib-2.7.dist-info/METADATA
fdplib-2.7.dist-info/WHEEL
fdplib-2.7.dist-info/top_level.txt
fdplib-2.7.dist-info/RECORD
