Metadata-Version: 2.1
Name: fdplib
Version: 2.7
Home-page: https://github.com/illini-motorsports/fdplib
Author: cmmeyer1800
Author-email: collinmmeyer@gmail.com
Requires-Python: >=3.6
Requires-Dist: tqdm (>=4.0)
Requires-Dist: numpy (>=1.0)
Requires-Dist: matplotlib (>=3.5)
